Workbook

Sheet Calculator
A1: Turabees Bespoke Wedding Wear Calculator
A2: Fill the yellow cells. Price per outfit = (Style base + Fabric + Embroidery) x (1 + mark-up). Add-ons and delivery are added after.
A4: Style | B4: Sherwani
A5: Fabric grade | B5: Standard blend
A6: Embroidery | B6: Light
A7: Quantity (outfits) | B7: 1
A8: Delivery (£) | B8: 0
A10: Add-ons (tick Yes)
A11: Add-on | B11: Include? | C11: Unit price | D11: Per | E11: Line total
A12: ='Price List'!A13 -> Fabric swatch pack (posted) | B12: No | C12: ='Price List'!B13 -> 5 | D12: ='Price List'!C13 -> order | E12: =IF(B12="Yes",C12*IF(D12="outfit",$B$7,1),0) -> 0
A13: ='Price List'!A14 -> Extra alteration round | B13: No | C13: ='Price List'!B14 -> 10 | D13: ='Price List'!C14 -> outfit | E13: =IF(B13="Yes",C13*IF(D13="outfit",$B$7,1),0) -> 0
A14: ='Price List'!A15 -> Rush production (peak season) | B14: No | C14: ='Price List'!B15 -> 30 | D14: ='Price List'!C15 -> outfit | E14: =IF(B14="Yes",C14*IF(D14="outfit",$B$7,1),0) -> 0
A15: ='Price List'!A16 -> Delay-compensation guarantee | B15: No | C15: ='Price List'!B16 -> 10 | D15: ='Price List'!C16 -> order | E15: =IF(B15="Yes",C15*IF(D15="outfit",$B$7,1),0) -> 0
A16: ='Price List'!A17 -> Extra piece (waistcoat / stole) | B16: No | C16: ='Price List'!B17 -> 20 | D16: ='Price List'!C17 -> outfit | E16: =IF(B16="Yes",C16*IF(D16="outfit",$B$7,1),0) -> 0
A17: ='Price List'!A18 -> Monogram / premium lining | B17: No | C17: ='Price List'!B18 -> 8 | D17: ='Price List'!C18 -> outfit | E17: =IF(B17="Yes",C17*IF(D17="outfit",$B$7,1),0) -> 0
A19: Result
A20: Style base | B20: =INDEX('Price List'!$D$4:$D$9,MATCH($B$4,'Price List'!$A$4:$A$9,0)) -> 50
A21: Fabric needed (m) | B21: =INDEX('Price List'!$C$4:$C$9,MATCH($B$4,'Price List'!$A$4:$A$9,0)) -> 4.5
A22: Fabric cost | B22: =B21*INDEX('Price List'!$J$4:$J$6,MATCH($B$5,'Price List'!$I$4:$I$6,0)) -> 45
A23: Embroidery | B23: =INDEX('Price List'!$G$4:$G$7,MATCH($B$6,'Price List'!$F$4:$F$7,0)) -> 20
A24: Subtotal | B24: =B20+B22+B23 -> 115
A25: Mark-up | B25: =B24*'Price List'!$N$4 -> 17.25
A26: PRICE PER OUTFIT (before add-ons and delivery) | B26: =B24+B25 -> 132.25
A27: Category | B27: =INDEX('Price List'!$B$4:$B$9,MATCH($B$4,'Price List'!$A$4:$A$9,0)) -> Sherwani
A28: Price zone (report) | B28: =IF(B27="Sherwani",INDEX('Price Zones'!$B$4:$B$8,MATCH(B26,'Price Zones'!$A$4:$A$8,1)),IF(B27="Suit",INDEX('Price Zones'!$E$4:$E$7,MATCH(B26,'Price Zones'!$D$4:$D$7,1)),INDEX('Price Zones'!$H$4:$H$6,MATCH(B26,'Price Zones'!$G$4:$G$6,1)))) -> Hesitation zone (£120-£150)
A29: Recommended window: low | B29: =INDEX('Price Zones'!$B$13:$B$15,MATCH(B27,'Price Zones'!$A$13:$A$15,0)) -> 150
A30: Recommended window: high | B30: =INDEX('Price Zones'!$C$13:$C$15,MATCH(B27,'Price Zones'!$A$13:$A$15,0)) -> 190
A31: Status | B31: =IF(B26<B29,"Below window by £"&TEXT(B29-B26,"0.00"),IF(B26>B30,"Above window by £"&TEXT(B26-B30,"0.00"),"Within recommended window")) -> Below window by £17.75
A32: Evidence needed | B32: =INDEX('Price Zones'!$E$13:$E$15,MATCH(B27,'Price Zones'!$A$13:$A$15,0)) -> Fabric swatches sent home + try-on / 2 fittings + free alterations + real wedding photos
A33: Embroidery check | B33: =IF(AND(B27="Tuxedo",B6<>"None",B26<150),"Embroidered tuxedo below £150: report says craft expectations not met","OK") -> OK
A34: Order
A35: Outfits total (price x quantity) | B35: =B26*B7 -> 132.25
A36: Add-ons total | B36: =SUM(E12:E17) -> 0
A37: Delivery | B37: =B8 -> 0
A38: ORDER TOTAL | B38: =B35+B36+B37 -> 132.25

Sheet Price List
A1: Price List
A2: Blue = editable input. Orange note = placeholder to replace with your real cost.
A3: Style | B3: Category | C3: Fabric (m) | D3: Style base (£) | F3: Embroidery tier | G3: Price (£) | I3: Fabric grade | J3: Rate per metre (£) | K3: Note | M3: Setting | N3: Value
A4: Sherwani | B4: Sherwani | C4: 4.5 | D4: 50 | F4: None | G4: 0 | I4: Standard blend | J4: 10 | K4: Your rate | M4: Mark-up | N4: 0.15
A5: 2-Piece Suit | B5: Suit | C5: 3 | D5: 40 | F5: Light | G5: 20 | I5: Silk blend | J5: 16 | K5: Placeholder: replace with supplier cost
A6: 3-Piece Suit | B6: Suit | C6: 3.6 | D6: 50 | F6: Medium | G6: 40 | I6: Jamawar / Velvet | J6: 24 | K6: Placeholder: replace with supplier cost
A7: Double-Breasted Suit | B7: Suit | C7: 3.4 | D7: 52 | F7: Heavy | G7: 80
A8: Tuxedo | B8: Tuxedo | C8: 3.2 | D8: 48
A9: Dinner Suit | B9: Tuxedo | C9: 3 | D9: 44
A11: Add-ons (added AFTER the mark-up, not marked up)
A12: Add-on | B12: Price (£) | C12: Charged per | D12: Note
A13: Fabric swatch pack (posted) | B13: 5 | C13: order | D13: Placeholder. Report: swatches are a hard gate for Sherwani; consider free or refundable
A14: Extra alteration round | B14: 10 | C14: outfit | D14: Report: 2 fittings/free alterations expected in price; extras optional
A15: Rush production (peak season) | B15: 30 | C15: outfit | D15: Placeholder. Standard production is 4-6 weeks
A16: Delay-compensation guarantee | B16: 10 | C16: order | D16: Placeholder. Report: written delay compensation builds trust
A17: Extra piece (waistcoat / stole) | B17: 20 | C17: outfit | D17: From v1 (£16-30 range)
A18: Monogram / premium lining | B18: 8 | C18: outfit | D18: From v1
A21: Changes vs v1 (based on simulation report)
A22: Sherwani fabric raised from 3.5 m to 4.5 m: the report's analysts say a Sherwani needs 4-5 m, so v1 under-costed fabric.
A23: Dinner Suit is mapped to the Tuxedo category and Double-Breasted to Suit (assumption; edit column B if you disagree).
A24: Added fabric grades: the report says £10/m cannot support real silk, jamawar or velvet. Grades 2 and 3 are placeholders.
A25: Added quantity (group orders of 5-8), report-based price zones, and an evidence checklist per category.

Sheet Price Zones
A1: Price Zones (from the simulation report)
A2: Zones are judged on price per outfit BEFORE add-ons and delivery. Thresholds are the lower bound of each zone.
A3: Sherwani from (£) | B3: Zone | D3: Suit from (£) | E3: Zone | G3: Tuxedo from (£) | H3: Zone
A4: 0 | B4: Quality-risk zone (below £120): reads as synthetic | D4: 0 | E4: Below £85: not credible as made-to-measure | G4: 0 | H4: Danger signal (below £100): read as fixed-block synthetic
A5: 120 | B5: Hesitation zone (£120-£150) | D5: 85 | E5: Reasonable made-to-measure zone (£85-£100) | G5: 100 | H5: Low-risk trial range (£100-£122)
A6: 150 | B6: BEST BALANCE (£150-£190): conditional acceptance | D6: 100 | E6: BEST BALANCE (£100-£122): made-to-measure + 2 alterations | G6: 122.01 | H6: Above range: justify with value (embroidered Indo-Western needs £150+)
A7: 190.01 | B7: Serious negotiation zone (£190-£380): needs physical proof | D7: 122.01 | E7: Overlaps local bespoke tailors: needs clear extra value
A8: 380.01 | B8: Core-circle decision zone (above £380)
A11: Recommended window and evidence needed by category
A12: Category | B12: Window low (£) | C12: Window high (£) | D12: Confidence | E12: Evidence needed to make the price credible
A13: Sherwani | B13: 150 | C13: 190 | D13: High | E13: Fabric swatches sent home + try-on / 2 fittings + free alterations + real wedding photos
A14: Suit | B14: 100 | C14: 122 | D14: Medium-high | E14: 21-day delivery in writing + 2 free alterations. Say 'made-to-measure', never 'fully bespoke'
A15: Tuxedo | B15: 100 | C15: 122 | D15: Medium | E15: Position separately from suits. Embroidered Indo-Western tuxedos need £150+ to match craft expectations

Sheet Price Grid
A1: Price Grid: every style x embroidery tier
A2: Price per outfit before add-ons and delivery. Green = inside the report's recommended window, red = below (trust risk), amber = above.
A3: Fabric grade: | B3: Standard blend
A4: Style | B4: Category | C4: Window low | D4: Window high | E4: ='Price List'!F4 -> None | F4: ='Price List'!F5 -> Light | G4: ='Price List'!F6 -> Medium | H4: ='Price List'!F7 -> Heavy
A5: ='Price List'!A4 -> Sherwani | B5: ='Price List'!B4 -> Sherwani | C5: =INDEX('Price Zones'!$B$13:$B$15,MATCH(B5,'Price Zones'!$A$13:$A$15,0)) -> 150 | D5: =INDEX('Price Zones'!$C$13:$C$15,MATCH(B5,'Price Zones'!$A$13:$A$15,0)) -> 190 | E5: =('Price List'!$D4+'Price List'!$C4*INDEX('Price List'!$J$4:$J$6,MATCH($B$3,'Price List'!$I$4:$I$6,0))+INDEX('Price List'!$G$4:$G$7,MATCH(E$4,'Price List'!$F$4:$F$7,0)))*(1+'Price List'!$N$4) -> 109.25 | F5: =('Price List'!$D4+'Price List'!$C4*INDEX('Price List'!$J$4:$J$6,MATCH($B$3,'Price List'!$I$4:$I$6,0))+INDEX('Price List'!$G$4:$G$7,MATCH(F$4,'Price List'!$F$4:$F$7,0)))*(1+'Price List'!$N$4) -> 132.25 | G5: =('Price List'!$D4+'Price List'!$C4*INDEX('Price List'!$J$4:$J$6,MATCH($B$3,'Price List'!$I$4:$I$6,0))+INDEX('Price List'!$G$4:$G$7,MATCH(G$4,'Price List'!$F$4:$F$7,0)))*(1+'Price List'!$N$4) -> 155.25 | H5: =('Price List'!$D4+'Price List'!$C4*INDEX('Price List'!$J$4:$J$6,MATCH($B$3,'Price List'!$I$4:$I$6,0))+INDEX('Price List'!$G$4:$G$7,MATCH(H$4,'Price List'!$F$4:$F$7,0)))*(1+'Price List'!$N$4) -> 201.25
A6: ='Price List'!A5 -> 2-Piece Suit | B6: ='Price List'!B5 -> Suit | C6: =INDEX('Price Zones'!$B$13:$B$15,MATCH(B6,'Price Zones'!$A$13:$A$15,0)) -> 100 | D6: =INDEX('Price Zones'!$C$13:$C$15,MATCH(B6,'Price Zones'!$A$13:$A$15,0)) -> 122 | E6: =('Price List'!$D5+'Price List'!$C5*INDEX('Price List'!$J$4:$J$6,MATCH($B$3,'Price List'!$I$4:$I$6,0))+INDEX('Price List'!$G$4:$G$7,MATCH(E$4,'Price List'!$F$4:$F$7,0)))*(1+'Price List'!$N$4) -> 80.5 | F6: =('Price List'!$D5+'Price List'!$C5*INDEX('Price List'!$J$4:$J$6,MATCH($B$3,'Price List'!$I$4:$I$6,0))+INDEX('Price List'!$G$4:$G$7,MATCH(F$4,'Price List'!$F$4:$F$7,0)))*(1+'Price List'!$N$4) -> 103.5 | G6: =('Price List'!$D5+'Price List'!$C5*INDEX('Price List'!$J$4:$J$6,MATCH($B$3,'Price List'!$I$4:$I$6,0))+INDEX('Price List'!$G$4:$G$7,MATCH(G$4,'Price List'!$F$4:$F$7,0)))*(1+'Price List'!$N$4) -> 126.5 | H6: =('Price List'!$D5+'Price List'!$C5*INDEX('Price List'!$J$4:$J$6,MATCH($B$3,'Price List'!$I$4:$I$6,0))+INDEX('Price List'!$G$4:$G$7,MATCH(H$4,'Price List'!$F$4:$F$7,0)))*(1+'Price List'!$N$4) -> 172.5
A7: ='Price List'!A6 -> 3-Piece Suit | B7: ='Price List'!B6 -> Suit | C7: =INDEX('Price Zones'!$B$13:$B$15,MATCH(B7,'Price Zones'!$A$13:$A$15,0)) -> 100 | D7: =INDEX('Price Zones'!$C$13:$C$15,MATCH(B7,'Price Zones'!$A$13:$A$15,0)) -> 122 | E7: =('Price List'!$D6+'Price List'!$C6*INDEX('Price List'!$J$4:$J$6,MATCH($B$3,'Price List'!$I$4:$I$6,0))+INDEX('Price List'!$G$4:$G$7,MATCH(E$4,'Price List'!$F$4:$F$7,0)))*(1+'Price List'!$N$4) -> 98.9 | F7: =('Price List'!$D6+'Price List'!$C6*INDEX('Price List'!$J$4:$J$6,MATCH($B$3,'Price List'!$I$4:$I$6,0))+INDEX('Price List'!$G$4:$G$7,MATCH(F$4,'Price List'!$F$4:$F$7,0)))*(1+'Price List'!$N$4) -> 121.9 | G7: =('Price List'!$D6+'Price List'!$C6*INDEX('Price List'!$J$4:$J$6,MATCH($B$3,'Price List'!$I$4:$I$6,0))+INDEX('Price List'!$G$4:$G$7,MATCH(G$4,'Price List'!$F$4:$F$7,0)))*(1+'Price List'!$N$4) -> 144.9 | H7: =('Price List'!$D6+'Price List'!$C6*INDEX('Price List'!$J$4:$J$6,MATCH($B$3,'Price List'!$I$4:$I$6,0))+INDEX('Price List'!$G$4:$G$7,MATCH(H$4,'Price List'!$F$4:$F$7,0)))*(1+'Price List'!$N$4) -> 190.9
A8: ='Price List'!A7 -> Double-Breasted Suit | B8: ='Price List'!B7 -> Suit | C8: =INDEX('Price Zones'!$B$13:$B$15,MATCH(B8,'Price Zones'!$A$13:$A$15,0)) -> 100 | D8: =INDEX('Price Zones'!$C$13:$C$15,MATCH(B8,'Price Zones'!$A$13:$A$15,0)) -> 122 | E8: =('Price List'!$D7+'Price List'!$C7*INDEX('Price List'!$J$4:$J$6,MATCH($B$3,'Price List'!$I$4:$I$6,0))+INDEX('Price List'!$G$4:$G$7,MATCH(E$4,'Price List'!$F$4:$F$7,0)))*(1+'Price List'!$N$4) -> 98.9 | F8: =('Price List'!$D7+'Price List'!$C7*INDEX('Price List'!$J$4:$J$6,MATCH($B$3,'Price List'!$I$4:$I$6,0))+INDEX('Price List'!$G$4:$G$7,MATCH(F$4,'Price List'!$F$4:$F$7,0)))*(1+'Price List'!$N$4) -> 121.9 | G8: =('Price List'!$D7+'Price List'!$C7*INDEX('Price List'!$J$4:$J$6,MATCH($B$3,'Price List'!$I$4:$I$6,0))+INDEX('Price List'!$G$4:$G$7,MATCH(G$4,'Price List'!$F$4:$F$7,0)))*(1+'Price List'!$N$4) -> 144.9 | H8: =('Price List'!$D7+'Price List'!$C7*INDEX('Price List'!$J$4:$J$6,MATCH($B$3,'Price List'!$I$4:$I$6,0))+INDEX('Price List'!$G$4:$G$7,MATCH(H$4,'Price List'!$F$4:$F$7,0)))*(1+'Price List'!$N$4) -> 190.9
A9: ='Price List'!A8 -> Tuxedo | B9: ='Price List'!B8 -> Tuxedo | C9: =INDEX('Price Zones'!$B$13:$B$15,MATCH(B9,'Price Zones'!$A$13:$A$15,0)) -> 100 | D9: =INDEX('Price Zones'!$C$13:$C$15,MATCH(B9,'Price Zones'!$A$13:$A$15,0)) -> 122 | E9: =('Price List'!$D8+'Price List'!$C8*INDEX('Price List'!$J$4:$J$6,MATCH($B$3,'Price List'!$I$4:$I$6,0))+INDEX('Price List'!$G$4:$G$7,MATCH(E$4,'Price List'!$F$4:$F$7,0)))*(1+'Price List'!$N$4) -> 92 | F9: =('Price List'!$D8+'Price List'!$C8*INDEX('Price List'!$J$4:$J$6,MATCH($B$3,'Price List'!$I$4:$I$6,0))+INDEX('Price List'!$G$4:$G$7,MATCH(F$4,'Price List'!$F$4:$F$7,0)))*(1+'Price List'!$N$4) -> 115 | G9: =('Price List'!$D8+'Price List'!$C8*INDEX('Price List'!$J$4:$J$6,MATCH($B$3,'Price List'!$I$4:$I$6,0))+INDEX('Price List'!$G$4:$G$7,MATCH(G$4,'Price List'!$F$4:$F$7,0)))*(1+'Price List'!$N$4) -> 138 | H9: =('Price List'!$D8+'Price List'!$C8*INDEX('Price List'!$J$4:$J$6,MATCH($B$3,'Price List'!$I$4:$I$6,0))+INDEX('Price List'!$G$4:$G$7,MATCH(H$4,'Price List'!$F$4:$F$7,0)))*(1+'Price List'!$N$4) -> 184
A10: ='Price List'!A9 -> Dinner Suit | B10: ='Price List'!B9 -> Tuxedo | C10: =INDEX('Price Zones'!$B$13:$B$15,MATCH(B10,'Price Zones'!$A$13:$A$15,0)) -> 100 | D10: =INDEX('Price Zones'!$C$13:$C$15,MATCH(B10,'Price Zones'!$A$13:$A$15,0)) -> 122 | E10: =('Price List'!$D9+'Price List'!$C9*INDEX('Price List'!$J$4:$J$6,MATCH($B$3,'Price List'!$I$4:$I$6,0))+INDEX('Price List'!$G$4:$G$7,MATCH(E$4,'Price List'!$F$4:$F$7,0)))*(1+'Price List'!$N$4) -> 85.1 | F10: =('Price List'!$D9+'Price List'!$C9*INDEX('Price List'!$J$4:$J$6,MATCH($B$3,'Price List'!$I$4:$I$6,0))+INDEX('Price List'!$G$4:$G$7,MATCH(F$4,'Price List'!$F$4:$F$7,0)))*(1+'Price List'!$N$4) -> 108.1 | G10: =('Price List'!$D9+'Price List'!$C9*INDEX('Price List'!$J$4:$J$6,MATCH($B$3,'Price List'!$I$4:$I$6,0))+INDEX('Price List'!$G$4:$G$7,MATCH(G$4,'Price List'!$F$4:$F$7,0)))*(1+'Price List'!$N$4) -> 131.1 | H10: =('Price List'!$D9+'Price List'!$C9*INDEX('Price List'!$J$4:$J$6,MATCH($B$3,'Price List'!$I$4:$I$6,0))+INDEX('Price List'!$G$4:$G$7,MATCH(H$4,'Price List'!$F$4:$F$7,0)))*(1+'Price List'!$N$4) -> 177.1

Sheet Report Findings
A1: Simulation report: what it means for pricing
A2: Source: MiroFish simulation (synthetic personas, not real customer data). Validate with real customers before committing.
A4: Topic | B4: Finding
A5: Headline | B5: Very low prices trigger a trust scrutiny, not excitement. At £98-£190 for a Sherwani the first reaction was 'too cheap to trust'.
A6: Decision order | B6: Delivery time > fit > fabric > price. Delays near a fixed wedding date are the worst outcome.
A7: Best price windows | B7: Sherwani £150-£190 (high confidence). Suits £100-£122 (medium-high). Tuxedos £100-£122 (medium).
A8: Fabric cost | B8: Analysts noted a Sherwani needs 4-5 m; at £10/m the formula can only support synthetic blends. Silk/jamawar/velvet need higher rates.
A9: Suits vs Sherwani | B9: Suit blocks are standardised, so cheaper prices are tolerated; embroidery and fabric make Sherwani grade obvious.
A10: Wording | B10: For suits use 'made-to-measure' (fully bespoke below £100 is read as fake). Embroidered Indo-Western tuxedos need £150+.
A11: Evidence (all three needed) | B11: 1) Fabric swatches posted home. 2) Real delivery / workshop photos, incl. different body types. 3) Written delivery date, alteration count and rework terms.
A12: Try-on guarantee | B12: Order one trial piece first, then the whole groomsmen set (5-8). Partner tailor try-on (e.g. Southall) builds trust fast.
A13: Delivery terms | B13: Standard 4-6 weeks, rush option, and written delay compensation or refund. 21-day delivery for suits was named as a strong offer.
A14: Risk 1 | B14: Low prices read as quality risk, not value.
A15: Risk 2 | B15: No try-on plus delivery delay can ruin the wedding: the hard constraint.
... A19: Gap in report | B19: The community-narrative section was incomplete (tool fragment). Platform-specific narratives were not covered.
